bgdbloomfilter.cpython-310-i386-linux-gnu.so
bgdbloomfilter.libs/libgcc_s-887de51c.so.1
bgdbloomfilter.libs/libstdc++-d6415257.so.6.0.33
bgdbloomfilter-0.0.6.dist-info/METADATA
bgdbloomfilter-0.0.6.dist-info/WHEEL
bgdbloomfilter-0.0.6.dist-info/top_level.txt
bgdbloomfilter-0.0.6.dist-info/RECORD
