Metadata-Version: 2.4
Name: bgdbloomfilter
Version: 0.0.6
Summary: Bloom Filter
Home-page: https://www.bgd.ed.tum.de/
Author: Martin Werner and contributors
Author-email: martin.werner@tum.de
Dynamic: author
Dynamic: author-email
Dynamic: home-page
Dynamic: summary
